<?xml version = '1.0' encoding = 'UTF-8'?>
<TableProxyOraclev12c class="oracle.dbtools.crest.model.design.storage.oracle.v12c.TableProxyOraclev12c" name="IF_HEAD_TO_HEAD" directorySegmentName="seg_0" id="4C47E57B-D733-7A51-9F6E-EBB191EBD626">
<createdBy>kucza</createdBy>
<createdTime>2020-10-10 08:25:56 UTC</createdTime>
<ownerDesignName>SCSDM</ownerDesignName>
<logging>YES</logging>
<partitionedRowMovement>DISABLE</partitionedRowMovement>
<segment>0AB6996B-CED8-1DAC-85A7-B6103ECB5F89</segment>
<tableSpace>FB90E6F5-901D-B69E-06B1-1E6424C269CB</tableSpace>
<temporaryChanged>false</temporaryChanged>
<accessDriverType>oracle_loader</accessDriverType>
<rejectLimit></rejectLimit>
<columnProxies itemClass="oracle.dbtools.crest.model.design.storage.oracle.v12c.ColumnProxyOraclev12c">
<ColumnProxy name="TEAM_RIGHT" id="0D97C99A-2446-3810-69C2-89527DA348EB">
<createdBy>kucza</createdBy>
<createdTime>2020-10-10 08:25:56 UTC</createdTime>
<ownerDesignName>SCSDM</ownerDesignName>
</ColumnProxy>
<ColumnProxy name="MATCH_DATE" id="22DC2E00-9ED8-062E-9CC8-3BE728FDB81C">
<createdBy>kucza</createdBy>
<createdTime>2020-10-10 08:25:56 UTC</createdTime>
<ownerDesignName>SCSDM</ownerDesignName>
</ColumnProxy>
<ColumnProxy name="TEAM_LEFT" id="8944F199-11FC-69D8-D83F-0EACDF8D7A5F">
<createdBy>kucza</createdBy>
<createdTime>2020-10-10 08:25:56 UTC</createdTime>
<ownerDesignName>SCSDM</ownerDesignName>
</ColumnProxy>
<ColumnProxy name="TOURNAMENT" id="9807DFCE-B70E-40ED-4503-51E77FC774EE">
<createdBy>kucza</createdBy>
<createdTime>2020-10-10 08:25:56 UTC</createdTime>
<ownerDesignName>SCSDM</ownerDesignName>
</ColumnProxy>
<ColumnProxy name="MATCH_URL" id="98F6FE0D-906D-D35B-D947-BBF557BEA043">
<createdBy>kucza</createdBy>
<createdTime>2020-10-10 08:25:56 UTC</createdTime>
<ownerDesignName>SCSDM</ownerDesignName>
</ColumnProxy>
<ColumnProxy name="SCORE" id="B4268562-FADE-201E-41F9-607C101296A4">
<createdBy>kucza</createdBy>
<createdTime>2020-10-10 08:25:56 UTC</createdTime>
<ownerDesignName>SCSDM</ownerDesignName>
</ColumnProxy>
<ColumnProxy name="T_INSERT_DTTM" id="C52C21EA-2D70-8C72-CA9F-D06F91A163DA">
<createdBy>kucza</createdBy>
<createdTime>2020-10-10 08:25:56 UTC</createdTime>
<ownerDesignName>SCSDM</ownerDesignName>
<defaultValue>current_timestamp</defaultValue>
</ColumnProxy>
<ColumnProxy name="MAP" id="E122A726-CFA2-6806-8F5F-F938E34FF322">
<createdBy>kucza</createdBy>
<createdTime>2020-10-10 08:25:56 UTC</createdTime>
<ownerDesignName>SCSDM</ownerDesignName>
</ColumnProxy>
</columnProxies>
</TableProxyOraclev12c>
